tz_detect/__init__.py
tz_detect/defaults.py
tz_detect/middleware.py
tz_detect/models.py
tz_detect/tests.py
tz_detect/urls.py
tz_detect/utils.py
tz_detect/views.py
tz_detect/static/tz_detect/js/tzdetect.js
tz_detect/static/tz_detect/js/tzdetect.min.js
tz_detect/templates/tz_detect/detector.html
tz_detect/templatetags/__init__.py
tz_detect/templatetags/tz_detect.py
django_tz_detect-0.4.0.dist-info/LICENSE
django_tz_detect-0.4.0.dist-info/METADATA
django_tz_detect-0.4.0.dist-info/WHEEL
django_tz_detect-0.4.0.dist-info/top_level.txt
django_tz_detect-0.4.0.dist-info/RECORD
