Metadata-Version: 2.1
Name: django-tz-detect
Version: 0.4.0
Summary: Automatic user timezone detection for django
Home-page: http://github.com/adamcharnock/django-tz-detect
Download-URL: https://github.com/adamcharnock/django-tz-detect/zipball/master
Author: Adam Charnock
Author-email: adam@adamcharnock.com
Maintainer: Basil Shubin
Maintainer-email: basil.shubin@gmail.com
License: MIT License
Platform: UNKNOWN
Classifier: Development Status :: 5 - Production/Stable
Classifier: Environment :: Web Environment
Classifier: Framework :: Django
Classifier: Intended Audience :: Developers
Classifier: License :: OSI Approved :: MIT License
Classifier: Operating System :: OS Independent
Classifier: Programming Language :: Python
Classifier: Programming Language :: Python :: 3
Classifier: Programming Language :: Python :: 3.7
Classifier: Programming Language :: Python :: 3.8
Classifier: Programming Language :: Python :: 3.9
Classifier: Programming Language :: Python :: 3.10
Classifier: Topic :: Internet :: WWW/HTTP
Classifier: Topic :: Internet :: WWW/HTTP :: Dynamic Content
License-File: LICENSE
